{"Kawiu": ["Ngân Hà Chiếu Nhụy", "Hoa Poppy Himalaya Xanh", "Dạ Yến Thảo Lam", "Lạp Mai đỏ", "Hoa Anh Thảo Hồng", "Hoa Anh Thảo Xanh", "Cây Holly Vòng Xanh", "Bụp Hồng Cận Hồng"], "ミ★Tài★Gió★彡": ["Lạp Mai đỏ", "Cây Sống Đời Đỏ", "Dạ Yến Thảo Lam", "Lan Phượng Vĩ Đỏ", "Lan Vũ Nữ Vàng", "Hoa Anh Thảo Hồng", "Thược Dược Đỏ", "Cây Holly Vòng Xanh", "Bụp Hồng Cận Hồng", "Hoa Lộ Vi Trắng"], "Tiểu tỷ tỷ": ["Hoa Hành Tím", "Địa Lan Trắng"], "Hoa phiêu": ["Dạ Yến Thảo Lam", "Bụp Hồng Cận Hồng", "Cây Holly Vòng Xanh"], "Sóc cute": ["Bụp Hồng Cận Hồng", "Cây Holly Vòng Xanh"], "Thuỳ Dun": [], "Angela0858": [], "Nấm Lùn": [], "Mỡ Xinh": [], "Ngân": [], "Ninh bình": [], "Mèo Lười": [], "Vườn Vân": [], "Người đẹp": [], "Ngư Ngư": [], "Hoa Phiêu": [], "Aniki Chen": []}